paulg/__init__.py
paulg/bel.py
paulg-0.4.0.dist-info/LICENSE
paulg-0.4.0.dist-info/WHEEL
paulg-0.4.0.dist-info/METADATA
paulg-0.4.0.dist-info/RECORD
